Metadata-Version: 2.1
Name: django-sap
Version: 1.0.0
Summary: Integration Sap
Home-page: https://gitlab.com/linets/ecommerce/oms/integrations/oms-sap/
Author: Linets team
Author-email: avelasqueza@linets.cl
License: MIT
Platform: UNKNOWN
Requires-Python: >=3.7
License-File: LICENSE
